pychemia/__init__.py
pychemia/setup.json
pychemia/analysis/__init__.py
pychemia/analysis/analysis.py
pychemia/analysis/changer.py
pychemia/analysis/cluster.py
pychemia/analysis/matching.py
pychemia/analysis/splitting.py
pychemia/analysis/surface.py
pychemia/code/__init__.py
pychemia/code/codes.py
pychemia/code/relaxator.py
pychemia/code/tasks.py
pychemia/code/abinit/__init__.py
pychemia/code/abinit/abifiles.py
pychemia/code/abinit/abinit.py
pychemia/code/abinit/htmlparser.py
pychemia/code/abinit/input.py
pychemia/code/abinit/output.py
pychemia/code/abinit/parser.py
pychemia/code/abinit/run.py
pychemia/code/abinit/utils.py
pychemia/code/abinit/task/__init__.py
pychemia/code/abinit/task/relax.py
pychemia/code/abinit/task/static.py
pychemia/code/dftb/__init__.py
pychemia/code/dftb/dftb.py
pychemia/code/dftb/input.py
pychemia/code/dftb/output.py
pychemia/code/dftb/task/__init__.py
pychemia/code/dftb/task/kpconv.py
pychemia/code/dftb/task/relax.py
pychemia/code/dftb/task/static.py
pychemia/code/elk/__init__.py
pychemia/code/elk/input.py
pychemia/code/elk/output.py
pychemia/code/elk/run.py
pychemia/code/fireball/__init__.py
pychemia/code/fireball/fireball.py
pychemia/code/fireball/input.py
pychemia/code/fireball/output.py
pychemia/code/fireball/task/__init__.py
pychemia/code/lennardjones/__init__.py
pychemia/code/lennardjones/lj.py
pychemia/code/new_fireball/__init__.py
pychemia/code/new_fireball/fireball.py
pychemia/code/octopus/__init__.py
pychemia/code/octopus/analysis.py
pychemia/code/octopus/input.py
pychemia/code/octopus/merge.py
pychemia/code/octopus/output.py
pychemia/code/octopus/run.py
pychemia/code/phonopy/__init__.py
pychemia/code/siesta/__init__.py
pychemia/code/siesta/input.py
pychemia/code/siesta/output.py
pychemia/code/siesta/run.py
pychemia/code/sprkkr/__init__.py
pychemia/code/vasp/__init__.py
pychemia/code/vasp/doscar.py
pychemia/code/vasp/incar.py
pychemia/code/vasp/input.py
pychemia-0.18.2.21.dist-info/DESCRIPTION.rst
pychemia-0.18.2.21.dist-info/METADATA
pychemia-0.18.2.21.dist-info/RECORD
pychemia-0.18.2.21.dist-info/WHEEL
pychemia-0.18.2.21.dist-info/metadata.json
pychemia-0.18.2.21.dist-info/top_level.txt
