Metadata-Version: 2.0
Name: pychemia
Version: 0.18.2.21
Summary: Python Framework for Materials Discovery and Design
Home-page: https://materialsdiscovery.github.io/PyChemia
Author: Guillermo Avendano-Franco
Author-email: gufranco@mail.wvu.edu
License: LICENSE.txt
Keywords: electronic,structure,analysis,materials,discovery,metaheuristics
Platform: UNKNOWN
Classifier: Development Status :: 4 - Beta
Classifier: Intended Audience :: Science/Research
Classifier: License :: OSI Approved :: MIT License
Classifier: Natural Language :: English
Classifier: Operating System :: POSIX
Classifier: Programming Language :: Python
Classifier: Programming Language :: Python :: 2
Classifier: Programming Language :: Python :: 2.7
Classifier: Programming Language :: Python :: 3
Classifier: Programming Language :: Python :: 3.4
Classifier: Programming Language :: Python :: 3.5
Classifier: Programming Language :: Python :: 3.6
Classifier: Topic :: Scientific/Engineering :: Chemistry
Classifier: Topic :: Scientific/Engineering :: Physics
Requires-Python: >=2.7, !=3.0.*, !=3.1.*, !=3.2.*, <4
Requires-Dist: numpy (>=1.12.0)
Requires-Dist: scipy (>=0.18.0)
Requires-Dist: future (>=0.16.0)
Requires-Dist: spglib (>=1.9.9)
Requires-Dist: pymongo (>=3.4.0)
